lektor_feed.py
lektor_feed-0.1.dist-info/DESCRIPTION.rst
lektor_feed-0.1.dist-info/METADATA
lektor_feed-0.1.dist-info/RECORD
lektor_feed-0.1.dist-info/WHEEL
lektor_feed-0.1.dist-info/entry_points.txt
lektor_feed-0.1.dist-info/metadata.json
lektor_feed-0.1.dist-info/top_level.txt
