Metadata-Version: 2.0
Name: lektor-feed
Version: 0.1
Summary: UNKNOWN
Home-page: https://yoyod.de/p/lektor-feed
Author: Detlef Kreuz
Author-email: mail-python.org@yodod.de
License: MIT
Platform: UNKNOWN
Requires-Dist: Lektor
Requires-Dist: MarkupSafe
